convert360/__init__.py
convert360/projector.py
convert360-0.1.3.data/scripts/convert360
convert360-0.1.3.dist-info/DESCRIPTION.rst
convert360-0.1.3.dist-info/METADATA
convert360-0.1.3.dist-info/RECORD
convert360-0.1.3.dist-info/WHEEL
convert360-0.1.3.dist-info/metadata.json
convert360-0.1.3.dist-info/top_level.txt
convert360-0.1.3.dist-info/zip-safe
