Metadata-Version: 2.0
Name: convert360
Version: 0.1.3
Summary: Tool to convert 360 videos between different projections.
Home-page: https://github.com/MateusZitelli/convert360
Author: Mateus Zitelli
Author-email: zitellimateus@gmail.com
License: GPLv3
Platform: UNKNOWN
Requires-Dist: PyOpenGL
Requires-Dist: imageio
Requires-Dist: tqdm
